string2datetime/__init__.py
string2datetime/string2datetime.py
string2datetime-0.0.1.dist-info/LICENSE
string2datetime-0.0.1.dist-info/METADATA
string2datetime-0.0.1.dist-info/WHEEL
string2datetime-0.0.1.dist-info/top_level.txt
string2datetime-0.0.1.dist-info/RECORD
