Metadata-Version: 2.1
Name: string2datetime
Version: 0.0.1
Summary: string to datetime
Home-page: https://github.com/BigDataFounder/string2date
Author: wangzekun
Author-email: 1656936@qq.com
License: MIT
Platform: UNKNOWN
License-File: LICENSE
